sababa/__init__.py
sababa/module1.py
sababa-0.0.4.dist-info/LICENSE
sababa-0.0.4.dist-info/METADATA
sababa-0.0.4.dist-info/WHEEL
sababa-0.0.4.dist-info/top_level.txt
sababa-0.0.4.dist-info/RECORD
