Metadata-Version: 2.1
Name: sababa
Version: 0.0.4
Summary: Sababa PyPI Package
Home-page: https://github.com/sababacloud/sababa-python
Author: sababa
Author-email: python@sababa.cloud
Project-URL: Documentation, https://github.com/sababacloud/sababa-python
Project-URL: Bug Reports, https://github.com/sababacloud/sababa-python/issues
Project-URL: Source Code, https://github.com/sababacloud/sababa-python
Keywords: sababa,pypi,package
Classifier: Development Status :: 1 - Planning
Classifier: Intended Audience :: Developers
Classifier: Topic :: Software Development
Classifier: Programming Language :: Python :: 3
Classifier: Programming Language :: Python :: 3.8
Classifier: Programming Language :: Python :: 3.9
Classifier: Programming Language :: Python :: 3 :: Only
Classifier: Operating System :: OS Independent
Requires-Python: >=3.6
License-File: LICENSE
Provides-Extra: dev
Requires-Dist: check-manifest ; extra == 'dev'
